paml2html/__init__.py
paml2html/paml2html.py
paml2html-0.1.1.dist-info/LICENSE
paml2html-0.1.1.dist-info/METADATA
paml2html-0.1.1.dist-info/WHEEL
paml2html-0.1.1.dist-info/RECORD
