Metadata-Version: 2.1
Name: paml2html
Version: 0.1.1
Summary: [P]oker's M[a]de-up [M]arkup [L]anguage to HTML converter
License: MIT
Author: PokerFacowaty
Author-email: pokerfacowaty.bn@gmail.com
Requires-Python: >=3.9,<4.0
Classifier: License :: OSI Approved :: MIT License
Classifier: Programming Language :: Python :: 3
Classifier: Programming Language :: Python :: 3.9
Classifier: Programming Language :: Python :: 3.10
Classifier: Programming Language :: Python :: 3.11
Requires-Dist: yattag (>=1.15.1,<2.0.0)
